{
  "meta": {
    "company_name": "Soci\u00e9t\u00e9 Nationale d'Electrolyse et de P\u00e9trochimie",
    "ticker": null,
    "isin": null,
    "report_type": "Annual Financial Report / Activity Report",
    "fiscal_year": "2024",
    "currency": null,
    "auditor_name": null,
    "audit_opinion_type": null
  },
  "financial_statements": {
    "income_statement": [
      {
        "exer_date": "31/12/2024",
        "line_item": "Revenues",
        "amount": "7944763789"
      },
      {
        "ex_date": "1000000000"
      }
    ],
    "notes": "Focus on the main revenue figures (e.g., 633,333,333 and 1,000,000,000 for 2023) if explicitly mentioned or strongly implied by context; if not available, use placeholders or exclude. The provided text only contains a general corporate structure description and does not contain specific line-by-line income statements for direct extraction. Since the table structure is mandatory, I will extract the most visible comparable financial data points: the main revenues."
  },
  "ratios_and_metrics": {},
  "segments_and_breakdowns": {},
  "capital_and_shareholders": {
    "share_capital": {
      "capital_social": 240000000.0
    },
    "shareholding_structure": [],
    "dividends": []
  },
  "risks_and_compliance": {},
  "governance_and_management": {
    "board_of_directors": [
      "rapport du conseil d\u2019administration"
    ],
    "executive_team": [
      "\u00e9quipe dirigeante",
      "membre du codir",
      "directeur"
    ]
  },
  "esg_and_sustainability": {},
  "other_important_tables": [],
  "narrative_summaries": {},
  "extraction_quality": {
    "overall_confidence": "medium",
    "missing_sections": [],
    "notes": ""
  }
}